<mxfile host="app.diagrams.net" modified="2023-07-26T06:56:33.075Z" agent="Mozilla/5.0 (Macintosh; Intel Mac OS X 10_15_7) AppleWebKit/537.36 (KHTML, like Gecko) Chrome/115.0.0.0 Safari/537.36" etag="FLGd6lNsSF2se8r6H-eh" version="21.6.5" type="github">
  <diagram id="C5RBs43oDa-KdzZeNtuy" name="Page-1">
    <mxGraphModel dx="636" dy="379" grid="1" gridSize="10" guides="1" tooltips="1" connect="1" arrows="1" fold="1" page="1" pageScale="1" pageWidth="1169" pageHeight="827" math="0" shadow="0">
      <root>
        <mxCell id="WIyWlLk6GJQsqaUBKTNV-0" />
        <mxCell id="WIyWlLk6GJQsqaUBKTNV-1" parent="WIyWlLk6GJQsqaUBKTNV-0" />
        <mxCell id="OIqggytlznoAPtVXcTWG-0" value="PASIEN" style="rounded=0;whiteSpace=wrap;html=1;" vertex="1" parent="WIyWlLk6GJQsqaUBKTNV-1">
          <mxGeometry x="520" y="360" width="120" height="40" as="geometry" />
        </mxCell>
        <mxCell id="OIqggytlznoAPtVXcTWG-1" value="&lt;font style=&quot;font-size: 9px;&quot;&gt;dikonsumsi&lt;/font&gt;" style="rhombus;whiteSpace=wrap;html=1;" vertex="1" parent="WIyWlLk6GJQsqaUBKTNV-1">
          <mxGeometry x="540" y="240" width="80" height="80" as="geometry" />
        </mxCell>
        <mxCell id="OIqggytlznoAPtVXcTWG-4" value="menepati" style="rhombus;whiteSpace=wrap;html=1;" vertex="1" parent="WIyWlLk6GJQsqaUBKTNV-1">
          <mxGeometry x="320" y="340" width="80" height="80" as="geometry" />
        </mxCell>
        <mxCell id="OIqggytlznoAPtVXcTWG-5" value="memeriksa" style="rhombus;whiteSpace=wrap;html=1;" vertex="1" parent="WIyWlLk6GJQsqaUBKTNV-1">
          <mxGeometry x="760" y="340" width="80" height="80" as="geometry" />
        </mxCell>
        <mxCell id="OIqggytlznoAPtVXcTWG-6" value="&lt;font style=&quot;font-size: 9px;&quot;&gt;alamat&lt;/font&gt;" style="rounded=0;whiteSpace=wrap;html=1;" vertex="1" parent="WIyWlLk6GJQsqaUBKTNV-1">
          <mxGeometry x="470" y="280" width="50" height="20" as="geometry" />
        </mxCell>
        <mxCell id="OIqggytlznoAPtVXcTWG-7" value="&lt;font style=&quot;font-size: 9px;&quot;&gt;no_telp&lt;/font&gt;" style="rounded=0;whiteSpace=wrap;html=1;" vertex="1" parent="WIyWlLk6GJQsqaUBKTNV-1">
          <mxGeometry x="450" y="310" width="50" height="20" as="geometry" />
        </mxCell>
        <mxCell id="OIqggytlznoAPtVXcTWG-8" value="&lt;font style=&quot;font-size: 9px;&quot;&gt;umur&lt;/font&gt;" style="rounded=0;whiteSpace=wrap;html=1;" vertex="1" parent="WIyWlLk6GJQsqaUBKTNV-1">
          <mxGeometry x="450" y="430" width="50" height="20" as="geometry" />
        </mxCell>
        <mxCell id="OIqggytlznoAPtVXcTWG-9" value="&lt;font style=&quot;font-size: 9px;&quot;&gt;keluhan&lt;/font&gt;" style="rounded=0;whiteSpace=wrap;html=1;" vertex="1" parent="WIyWlLk6GJQsqaUBKTNV-1">
          <mxGeometry x="470" y="460" width="50" height="20" as="geometry" />
        </mxCell>
        <mxCell id="OIqggytlznoAPtVXcTWG-10" value="&lt;font style=&quot;font-size: 9px;&quot;&gt;id_pasien&lt;/font&gt;" style="rounded=0;whiteSpace=wrap;html=1;" vertex="1" parent="WIyWlLk6GJQsqaUBKTNV-1">
          <mxGeometry x="640" y="280" width="50" height="20" as="geometry" />
        </mxCell>
        <mxCell id="OIqggytlznoAPtVXcTWG-11" value="&lt;font style=&quot;font-size: 7px;&quot;&gt;nama_pasien&lt;/font&gt;" style="rounded=0;whiteSpace=wrap;html=1;" vertex="1" parent="WIyWlLk6GJQsqaUBKTNV-1">
          <mxGeometry x="660" y="310" width="50" height="20" as="geometry" />
        </mxCell>
        <mxCell id="OIqggytlznoAPtVXcTWG-12" value="" style="endArrow=none;html=1;rounded=0;exitX=0.812;exitY=0.003;exitDx=0;exitDy=0;exitPerimeter=0;" edge="1" parent="WIyWlLk6GJQsqaUBKTNV-1" source="OIqggytlznoAPtVXcTWG-0">
          <mxGeometry width="50" height="50" relative="1" as="geometry">
            <mxPoint x="590" y="350" as="sourcePoint" />
            <mxPoint x="640" y="300" as="targetPoint" />
          </mxGeometry>
        </mxCell>
        <mxCell id="OIqggytlznoAPtVXcTWG-13" value="" style="endArrow=none;html=1;rounded=0;" edge="1" parent="WIyWlLk6GJQsqaUBKTNV-1">
          <mxGeometry width="50" height="50" relative="1" as="geometry">
            <mxPoint x="630" y="360" as="sourcePoint" />
            <mxPoint x="660" y="330" as="targetPoint" />
          </mxGeometry>
        </mxCell>
        <mxCell id="OIqggytlznoAPtVXcTWG-14" value="" style="endArrow=none;html=1;rounded=0;exitX=0.139;exitY=0.003;exitDx=0;exitDy=0;exitPerimeter=0;" edge="1" parent="WIyWlLk6GJQsqaUBKTNV-1" source="OIqggytlznoAPtVXcTWG-0">
          <mxGeometry width="50" height="50" relative="1" as="geometry">
            <mxPoint x="497" y="360" as="sourcePoint" />
            <mxPoint x="520" y="300" as="targetPoint" />
          </mxGeometry>
        </mxCell>
        <mxCell id="OIqggytlznoAPtVXcTWG-15" value="" style="endArrow=none;html=1;rounded=0;exitX=0.046;exitY=0.005;exitDx=0;exitDy=0;exitPerimeter=0;" edge="1" parent="WIyWlLk6GJQsqaUBKTNV-1" source="OIqggytlznoAPtVXcTWG-0">
          <mxGeometry width="50" height="50" relative="1" as="geometry">
            <mxPoint x="470" y="360" as="sourcePoint" />
            <mxPoint x="500" y="330" as="targetPoint" />
          </mxGeometry>
        </mxCell>
        <mxCell id="OIqggytlznoAPtVXcTWG-16" value="" style="endArrow=none;html=1;rounded=0;exitX=0.812;exitY=0.003;exitDx=0;exitDy=0;exitPerimeter=0;" edge="1" parent="WIyWlLk6GJQsqaUBKTNV-1">
          <mxGeometry width="50" height="50" relative="1" as="geometry">
            <mxPoint x="520" y="460" as="sourcePoint" />
            <mxPoint x="543" y="400" as="targetPoint" />
          </mxGeometry>
        </mxCell>
        <mxCell id="OIqggytlznoAPtVXcTWG-17" value="" style="endArrow=none;html=1;rounded=0;" edge="1" parent="WIyWlLk6GJQsqaUBKTNV-1">
          <mxGeometry width="50" height="50" relative="1" as="geometry">
            <mxPoint x="500" y="430" as="sourcePoint" />
            <mxPoint x="530" y="400" as="targetPoint" />
          </mxGeometry>
        </mxCell>
        <mxCell id="OIqggytlznoAPtVXcTWG-18" value="tgl_keluar" style="rounded=0;whiteSpace=wrap;html=1;" vertex="1" parent="WIyWlLk6GJQsqaUBKTNV-1">
          <mxGeometry x="300" y="280" width="120" height="40" as="geometry" />
        </mxCell>
        <mxCell id="OIqggytlznoAPtVXcTWG-19" value="tgl_masuk" style="rounded=0;whiteSpace=wrap;html=1;" vertex="1" parent="WIyWlLk6GJQsqaUBKTNV-1">
          <mxGeometry x="300" y="440" width="120" height="40" as="geometry" />
        </mxCell>
        <mxCell id="OIqggytlznoAPtVXcTWG-20" value="jam_periksa" style="rounded=0;whiteSpace=wrap;html=1;" vertex="1" parent="WIyWlLk6GJQsqaUBKTNV-1">
          <mxGeometry x="740" y="440" width="120" height="40" as="geometry" />
        </mxCell>
        <mxCell id="OIqggytlznoAPtVXcTWG-22" value="dokter" style="rounded=0;whiteSpace=wrap;html=1;" vertex="1" parent="WIyWlLk6GJQsqaUBKTNV-1">
          <mxGeometry x="960" y="360" width="120" height="40" as="geometry" />
        </mxCell>
        <mxCell id="OIqggytlznoAPtVXcTWG-23" value="kamar" style="rounded=0;whiteSpace=wrap;html=1;" vertex="1" parent="WIyWlLk6GJQsqaUBKTNV-1">
          <mxGeometry x="80" y="360" width="120" height="40" as="geometry" />
        </mxCell>
        <mxCell id="OIqggytlznoAPtVXcTWG-24" value="" style="endArrow=none;html=1;rounded=0;entryX=0;entryY=0.5;entryDx=0;entryDy=0;" edge="1" parent="WIyWlLk6GJQsqaUBKTNV-1" target="OIqggytlznoAPtVXcTWG-0">
          <mxGeometry width="50" height="50" relative="1" as="geometry">
            <mxPoint x="400" y="380" as="sourcePoint" />
            <mxPoint x="450" y="330" as="targetPoint" />
          </mxGeometry>
        </mxCell>
        <mxCell id="OIqggytlznoAPtVXcTWG-25" value="1" style="edgeLabel;html=1;align=center;verticalAlign=middle;resizable=0;points=[];" vertex="1" connectable="0" parent="OIqggytlznoAPtVXcTWG-24">
          <mxGeometry x="-0.0667" y="-1" relative="1" as="geometry">
            <mxPoint as="offset" />
          </mxGeometry>
        </mxCell>
        <mxCell id="OIqggytlznoAPtVXcTWG-26" value="" style="endArrow=none;html=1;rounded=0;entryX=0;entryY=0.5;entryDx=0;entryDy=0;" edge="1" parent="WIyWlLk6GJQsqaUBKTNV-1">
          <mxGeometry width="50" height="50" relative="1" as="geometry">
            <mxPoint x="200" y="379.62" as="sourcePoint" />
            <mxPoint x="320" y="379.62" as="targetPoint" />
          </mxGeometry>
        </mxCell>
        <mxCell id="OIqggytlznoAPtVXcTWG-27" value="1" style="edgeLabel;html=1;align=center;verticalAlign=middle;resizable=0;points=[];" vertex="1" connectable="0" parent="OIqggytlznoAPtVXcTWG-26">
          <mxGeometry x="-0.0667" y="-1" relative="1" as="geometry">
            <mxPoint as="offset" />
          </mxGeometry>
        </mxCell>
        <mxCell id="OIqggytlznoAPtVXcTWG-28" value="" style="endArrow=none;html=1;rounded=0;entryX=0;entryY=0.5;entryDx=0;entryDy=0;" edge="1" parent="WIyWlLk6GJQsqaUBKTNV-1">
          <mxGeometry width="50" height="50" relative="1" as="geometry">
            <mxPoint x="640" y="379.62" as="sourcePoint" />
            <mxPoint x="760" y="379.62" as="targetPoint" />
          </mxGeometry>
        </mxCell>
        <mxCell id="OIqggytlznoAPtVXcTWG-29" value="n" style="edgeLabel;html=1;align=center;verticalAlign=middle;resizable=0;points=[];" vertex="1" connectable="0" parent="OIqggytlznoAPtVXcTWG-28">
          <mxGeometry x="-0.0667" y="-1" relative="1" as="geometry">
            <mxPoint as="offset" />
          </mxGeometry>
        </mxCell>
        <mxCell id="OIqggytlznoAPtVXcTWG-31" value="" style="endArrow=none;html=1;rounded=0;entryX=0;entryY=0.5;entryDx=0;entryDy=0;" edge="1" parent="WIyWlLk6GJQsqaUBKTNV-1">
          <mxGeometry width="50" height="50" relative="1" as="geometry">
            <mxPoint x="840" y="379.75" as="sourcePoint" />
            <mxPoint x="960" y="379.75" as="targetPoint" />
          </mxGeometry>
        </mxCell>
        <mxCell id="OIqggytlznoAPtVXcTWG-32" value="n" style="edgeLabel;html=1;align=center;verticalAlign=middle;resizable=0;points=[];" vertex="1" connectable="0" parent="OIqggytlznoAPtVXcTWG-31">
          <mxGeometry x="-0.0667" y="-1" relative="1" as="geometry">
            <mxPoint as="offset" />
          </mxGeometry>
        </mxCell>
        <mxCell id="OIqggytlznoAPtVXcTWG-33" value="" style="endArrow=none;html=1;rounded=0;" edge="1" parent="WIyWlLk6GJQsqaUBKTNV-1">
          <mxGeometry width="50" height="50" relative="1" as="geometry">
            <mxPoint x="579.5" y="400" as="sourcePoint" />
            <mxPoint x="580" y="720" as="targetPoint" />
          </mxGeometry>
        </mxCell>
        <mxCell id="OIqggytlznoAPtVXcTWG-34" value="n" style="edgeLabel;html=1;align=center;verticalAlign=middle;resizable=0;points=[];" vertex="1" connectable="0" parent="OIqggytlznoAPtVXcTWG-33">
          <mxGeometry x="-0.0667" y="-1" relative="1" as="geometry">
            <mxPoint as="offset" />
          </mxGeometry>
        </mxCell>
        <mxCell id="OIqggytlznoAPtVXcTWG-35" value="" style="endArrow=none;html=1;rounded=0;" edge="1" parent="WIyWlLk6GJQsqaUBKTNV-1" target="OIqggytlznoAPtVXcTWG-22">
          <mxGeometry width="50" height="50" relative="1" as="geometry">
            <mxPoint x="1020" y="320" as="sourcePoint" />
            <mxPoint x="1100" y="230" as="targetPoint" />
          </mxGeometry>
        </mxCell>
        <mxCell id="OIqggytlznoAPtVXcTWG-36" value="1" style="edgeLabel;html=1;align=center;verticalAlign=middle;resizable=0;points=[];" vertex="1" connectable="0" parent="OIqggytlznoAPtVXcTWG-35">
          <mxGeometry x="-0.0667" y="-1" relative="1" as="geometry">
            <mxPoint as="offset" />
          </mxGeometry>
        </mxCell>
        <mxCell id="OIqggytlznoAPtVXcTWG-37" value="" style="endArrow=none;html=1;rounded=0;" edge="1" parent="WIyWlLk6GJQsqaUBKTNV-1">
          <mxGeometry width="50" height="50" relative="1" as="geometry">
            <mxPoint x="1019.89" y="400" as="sourcePoint" />
            <mxPoint x="1020" y="480" as="targetPoint" />
          </mxGeometry>
        </mxCell>
        <mxCell id="OIqggytlznoAPtVXcTWG-38" value="1" style="edgeLabel;html=1;align=center;verticalAlign=middle;resizable=0;points=[];" vertex="1" connectable="0" parent="OIqggytlznoAPtVXcTWG-37">
          <mxGeometry x="-0.0667" y="-1" relative="1" as="geometry">
            <mxPoint as="offset" />
          </mxGeometry>
        </mxCell>
        <mxCell id="OIqggytlznoAPtVXcTWG-39" value="menentukan" style="rhombus;whiteSpace=wrap;html=1;" vertex="1" parent="WIyWlLk6GJQsqaUBKTNV-1">
          <mxGeometry x="980" y="240" width="80" height="80" as="geometry" />
        </mxCell>
        <mxCell id="OIqggytlznoAPtVXcTWG-40" value="" style="endArrow=none;html=1;rounded=0;" edge="1" parent="WIyWlLk6GJQsqaUBKTNV-1">
          <mxGeometry width="50" height="50" relative="1" as="geometry">
            <mxPoint x="1019.71" y="200" as="sourcePoint" />
            <mxPoint x="1019.71" y="240" as="targetPoint" />
          </mxGeometry>
        </mxCell>
        <mxCell id="OIqggytlznoAPtVXcTWG-41" value="n" style="edgeLabel;html=1;align=center;verticalAlign=middle;resizable=0;points=[];" vertex="1" connectable="0" parent="OIqggytlznoAPtVXcTWG-40">
          <mxGeometry x="-0.0667" y="-1" relative="1" as="geometry">
            <mxPoint as="offset" />
          </mxGeometry>
        </mxCell>
        <mxCell id="OIqggytlznoAPtVXcTWG-42" value="" style="endArrow=none;html=1;rounded=0;exitX=0;exitY=0;exitDx=0;exitDy=0;" edge="1" parent="WIyWlLk6GJQsqaUBKTNV-1" source="OIqggytlznoAPtVXcTWG-22">
          <mxGeometry width="50" height="50" relative="1" as="geometry">
            <mxPoint x="960" y="340" as="sourcePoint" />
            <mxPoint x="940" y="340" as="targetPoint" />
          </mxGeometry>
        </mxCell>
        <mxCell id="OIqggytlznoAPtVXcTWG-43" value="" style="endArrow=none;html=1;rounded=0;exitX=0;exitY=0;exitDx=0;exitDy=0;" edge="1" parent="WIyWlLk6GJQsqaUBKTNV-1">
          <mxGeometry width="50" height="50" relative="1" as="geometry">
            <mxPoint x="1100" y="420" as="sourcePoint" />
            <mxPoint x="1080" y="400" as="targetPoint" />
          </mxGeometry>
        </mxCell>
        <mxCell id="OIqggytlznoAPtVXcTWG-44" value="" style="endArrow=none;html=1;rounded=0;entryX=0;entryY=1;entryDx=0;entryDy=0;" edge="1" parent="WIyWlLk6GJQsqaUBKTNV-1" target="OIqggytlznoAPtVXcTWG-22">
          <mxGeometry width="50" height="50" relative="1" as="geometry">
            <mxPoint x="940" y="420" as="sourcePoint" />
            <mxPoint x="950" y="350" as="targetPoint" />
          </mxGeometry>
        </mxCell>
        <mxCell id="OIqggytlznoAPtVXcTWG-45" value="" style="endArrow=none;html=1;rounded=0;entryX=0;entryY=1;entryDx=0;entryDy=0;" edge="1" parent="WIyWlLk6GJQsqaUBKTNV-1">
          <mxGeometry width="50" height="50" relative="1" as="geometry">
            <mxPoint x="1080" y="360" as="sourcePoint" />
            <mxPoint x="1100" y="340" as="targetPoint" />
          </mxGeometry>
        </mxCell>
        <mxCell id="OIqggytlznoAPtVXcTWG-47" value="&lt;span style=&quot;font-size: 7px;&quot;&gt;nama_dokter&lt;/span&gt;" style="rounded=0;whiteSpace=wrap;html=1;" vertex="1" parent="WIyWlLk6GJQsqaUBKTNV-1">
          <mxGeometry x="890" y="320" width="50" height="20" as="geometry" />
        </mxCell>
        <mxCell id="OIqggytlznoAPtVXcTWG-48" value="&lt;span style=&quot;font-size: 7px;&quot;&gt;jam_periksa&lt;/span&gt;" style="rounded=0;whiteSpace=wrap;html=1;" vertex="1" parent="WIyWlLk6GJQsqaUBKTNV-1">
          <mxGeometry x="890" y="420" width="50" height="20" as="geometry" />
        </mxCell>
        <mxCell id="OIqggytlznoAPtVXcTWG-49" value="&lt;span style=&quot;font-size: 7px;&quot;&gt;id_dokter&lt;/span&gt;" style="rounded=0;whiteSpace=wrap;html=1;" vertex="1" parent="WIyWlLk6GJQsqaUBKTNV-1">
          <mxGeometry x="1100" y="320" width="50" height="20" as="geometry" />
        </mxCell>
        <mxCell id="OIqggytlznoAPtVXcTWG-50" value="&lt;span style=&quot;font-size: 7px;&quot;&gt;no_telp&lt;/span&gt;" style="rounded=0;whiteSpace=wrap;html=1;" vertex="1" parent="WIyWlLk6GJQsqaUBKTNV-1">
          <mxGeometry x="1100" y="420" width="50" height="20" as="geometry" />
        </mxCell>
        <mxCell id="OIqggytlznoAPtVXcTWG-51" value="" style="endArrow=none;html=1;rounded=0;" edge="1" parent="WIyWlLk6GJQsqaUBKTNV-1">
          <mxGeometry width="50" height="50" relative="1" as="geometry">
            <mxPoint x="1080" y="380" as="sourcePoint" />
            <mxPoint x="1100" y="380" as="targetPoint" />
          </mxGeometry>
        </mxCell>
        <mxCell id="OIqggytlznoAPtVXcTWG-52" value="&lt;span style=&quot;font-size: 7px;&quot;&gt;alamat&lt;/span&gt;" style="rounded=0;whiteSpace=wrap;html=1;" vertex="1" parent="WIyWlLk6GJQsqaUBKTNV-1">
          <mxGeometry x="1100" y="370" width="50" height="20" as="geometry" />
        </mxCell>
        <mxCell id="OIqggytlznoAPtVXcTWG-53" value="obat" style="rounded=0;whiteSpace=wrap;html=1;" vertex="1" parent="WIyWlLk6GJQsqaUBKTNV-1">
          <mxGeometry x="960" y="160" width="120" height="40" as="geometry" />
        </mxCell>
        <mxCell id="OIqggytlznoAPtVXcTWG-55" value="" style="endArrow=none;html=1;rounded=0;entryX=0;entryY=1;entryDx=0;entryDy=0;" edge="1" parent="WIyWlLk6GJQsqaUBKTNV-1">
          <mxGeometry width="50" height="50" relative="1" as="geometry">
            <mxPoint x="1080" y="160" as="sourcePoint" />
            <mxPoint x="1100" y="140" as="targetPoint" />
          </mxGeometry>
        </mxCell>
        <mxCell id="OIqggytlznoAPtVXcTWG-56" value="" style="endArrow=none;html=1;rounded=0;exitX=0;exitY=0;exitDx=0;exitDy=0;" edge="1" parent="WIyWlLk6GJQsqaUBKTNV-1">
          <mxGeometry width="50" height="50" relative="1" as="geometry">
            <mxPoint x="960" y="160" as="sourcePoint" />
            <mxPoint x="940" y="140" as="targetPoint" />
          </mxGeometry>
        </mxCell>
        <mxCell id="OIqggytlznoAPtVXcTWG-57" value="" style="endArrow=none;html=1;rounded=0;entryX=0;entryY=1;entryDx=0;entryDy=0;" edge="1" parent="WIyWlLk6GJQsqaUBKTNV-1">
          <mxGeometry width="50" height="50" relative="1" as="geometry">
            <mxPoint x="940" y="220" as="sourcePoint" />
            <mxPoint x="960" y="200" as="targetPoint" />
          </mxGeometry>
        </mxCell>
        <mxCell id="OIqggytlznoAPtVXcTWG-60" value="" style="endArrow=none;html=1;rounded=0;exitX=0;exitY=0;exitDx=0;exitDy=0;" edge="1" parent="WIyWlLk6GJQsqaUBKTNV-1">
          <mxGeometry width="50" height="50" relative="1" as="geometry">
            <mxPoint x="1100" y="220" as="sourcePoint" />
            <mxPoint x="1080" y="200" as="targetPoint" />
          </mxGeometry>
        </mxCell>
        <mxCell id="OIqggytlznoAPtVXcTWG-61" value="&lt;span style=&quot;font-size: 7px;&quot;&gt;masa_berlaku&lt;/span&gt;" style="rounded=0;whiteSpace=wrap;html=1;" vertex="1" parent="WIyWlLk6GJQsqaUBKTNV-1">
          <mxGeometry x="890" y="120" width="50" height="20" as="geometry" />
        </mxCell>
        <mxCell id="OIqggytlznoAPtVXcTWG-62" value="&lt;span style=&quot;font-size: 7px;&quot;&gt;kode_obat&lt;/span&gt;" style="rounded=0;whiteSpace=wrap;html=1;" vertex="1" parent="WIyWlLk6GJQsqaUBKTNV-1">
          <mxGeometry x="1090" y="220" width="50" height="20" as="geometry" />
        </mxCell>
        <mxCell id="OIqggytlznoAPtVXcTWG-63" value="&lt;span style=&quot;font-size: 7px;&quot;&gt;jenis_obat&lt;/span&gt;" style="rounded=0;whiteSpace=wrap;html=1;" vertex="1" parent="WIyWlLk6GJQsqaUBKTNV-1">
          <mxGeometry x="1100" y="120" width="50" height="20" as="geometry" />
        </mxCell>
        <mxCell id="OIqggytlznoAPtVXcTWG-64" value="&lt;span style=&quot;font-size: 7px;&quot;&gt;nama_obat&lt;/span&gt;" style="rounded=0;whiteSpace=wrap;html=1;" vertex="1" parent="WIyWlLk6GJQsqaUBKTNV-1">
          <mxGeometry x="890" y="220" width="50" height="20" as="geometry" />
        </mxCell>
        <mxCell id="OIqggytlznoAPtVXcTWG-66" value="" style="endArrow=none;html=1;rounded=0;" edge="1" parent="WIyWlLk6GJQsqaUBKTNV-1">
          <mxGeometry width="50" height="50" relative="1" as="geometry">
            <mxPoint x="960" y="279.78" as="sourcePoint" />
            <mxPoint x="980" y="279.78" as="targetPoint" />
          </mxGeometry>
        </mxCell>
        <mxCell id="OIqggytlznoAPtVXcTWG-67" value="&lt;span style=&quot;font-size: 7px;&quot;&gt;diagnosa&lt;/span&gt;" style="rounded=0;whiteSpace=wrap;html=1;" vertex="1" parent="WIyWlLk6GJQsqaUBKTNV-1">
          <mxGeometry x="910" y="270" width="50" height="20" as="geometry" />
        </mxCell>
        <mxCell id="OIqggytlznoAPtVXcTWG-68" value="membantu" style="rhombus;whiteSpace=wrap;html=1;" vertex="1" parent="WIyWlLk6GJQsqaUBKTNV-1">
          <mxGeometry x="980" y="480" width="80" height="80" as="geometry" />
        </mxCell>
        <mxCell id="OIqggytlznoAPtVXcTWG-69" value="" style="endArrow=none;html=1;rounded=0;" edge="1" parent="WIyWlLk6GJQsqaUBKTNV-1">
          <mxGeometry width="50" height="50" relative="1" as="geometry">
            <mxPoint x="1019.7" y="560" as="sourcePoint" />
            <mxPoint x="1019.7" y="600" as="targetPoint" />
          </mxGeometry>
        </mxCell>
        <mxCell id="OIqggytlznoAPtVXcTWG-70" value="n" style="edgeLabel;html=1;align=center;verticalAlign=middle;resizable=0;points=[];" vertex="1" connectable="0" parent="OIqggytlznoAPtVXcTWG-69">
          <mxGeometry x="-0.0667" y="-1" relative="1" as="geometry">
            <mxPoint as="offset" />
          </mxGeometry>
        </mxCell>
        <mxCell id="OIqggytlznoAPtVXcTWG-71" value="perawat" style="rounded=0;whiteSpace=wrap;html=1;" vertex="1" parent="WIyWlLk6GJQsqaUBKTNV-1">
          <mxGeometry x="960" y="600" width="120" height="40" as="geometry" />
        </mxCell>
        <mxCell id="OIqggytlznoAPtVXcTWG-72" value="" style="endArrow=none;html=1;rounded=0;entryX=0;entryY=1;entryDx=0;entryDy=0;" edge="1" parent="WIyWlLk6GJQsqaUBKTNV-1">
          <mxGeometry width="50" height="50" relative="1" as="geometry">
            <mxPoint x="940" y="660" as="sourcePoint" />
            <mxPoint x="960" y="640" as="targetPoint" />
          </mxGeometry>
        </mxCell>
        <mxCell id="OIqggytlznoAPtVXcTWG-73" value="" style="endArrow=none;html=1;rounded=0;exitX=0;exitY=0;exitDx=0;exitDy=0;" edge="1" parent="WIyWlLk6GJQsqaUBKTNV-1">
          <mxGeometry width="50" height="50" relative="1" as="geometry">
            <mxPoint x="1100" y="660" as="sourcePoint" />
            <mxPoint x="1080" y="640" as="targetPoint" />
          </mxGeometry>
        </mxCell>
        <mxCell id="OIqggytlznoAPtVXcTWG-74" value="" style="endArrow=none;html=1;rounded=0;entryX=0;entryY=1;entryDx=0;entryDy=0;" edge="1" parent="WIyWlLk6GJQsqaUBKTNV-1">
          <mxGeometry width="50" height="50" relative="1" as="geometry">
            <mxPoint x="1080" y="600" as="sourcePoint" />
            <mxPoint x="1100" y="580" as="targetPoint" />
          </mxGeometry>
        </mxCell>
        <mxCell id="OIqggytlznoAPtVXcTWG-75" value="" style="endArrow=none;html=1;rounded=0;exitX=0;exitY=0;exitDx=0;exitDy=0;" edge="1" parent="WIyWlLk6GJQsqaUBKTNV-1">
          <mxGeometry width="50" height="50" relative="1" as="geometry">
            <mxPoint x="960" y="600" as="sourcePoint" />
            <mxPoint x="940" y="580" as="targetPoint" />
          </mxGeometry>
        </mxCell>
        <mxCell id="OIqggytlznoAPtVXcTWG-76" value="" style="endArrow=none;html=1;rounded=0;" edge="1" parent="WIyWlLk6GJQsqaUBKTNV-1">
          <mxGeometry width="50" height="50" relative="1" as="geometry">
            <mxPoint x="1080" y="619.92" as="sourcePoint" />
            <mxPoint x="1100" y="619.92" as="targetPoint" />
          </mxGeometry>
        </mxCell>
        <mxCell id="OIqggytlznoAPtVXcTWG-77" value="&lt;span style=&quot;font-size: 7px;&quot;&gt;no_telp&lt;/span&gt;" style="rounded=0;whiteSpace=wrap;html=1;" vertex="1" parent="WIyWlLk6GJQsqaUBKTNV-1">
          <mxGeometry x="1100" y="660" width="50" height="20" as="geometry" />
        </mxCell>
        <mxCell id="OIqggytlznoAPtVXcTWG-78" value="&lt;span style=&quot;font-size: 7px;&quot;&gt;no_telp&lt;/span&gt;" style="rounded=0;whiteSpace=wrap;html=1;" vertex="1" parent="WIyWlLk6GJQsqaUBKTNV-1">
          <mxGeometry x="1100" y="610" width="50" height="20" as="geometry" />
        </mxCell>
        <mxCell id="OIqggytlznoAPtVXcTWG-79" value="&lt;span style=&quot;font-size: 7px;&quot;&gt;no_telp&lt;/span&gt;" style="rounded=0;whiteSpace=wrap;html=1;" vertex="1" parent="WIyWlLk6GJQsqaUBKTNV-1">
          <mxGeometry x="1100" y="560" width="50" height="20" as="geometry" />
        </mxCell>
        <mxCell id="OIqggytlznoAPtVXcTWG-80" value="&lt;span style=&quot;font-size: 7px;&quot;&gt;no_telp&lt;/span&gt;" style="rounded=0;whiteSpace=wrap;html=1;" vertex="1" parent="WIyWlLk6GJQsqaUBKTNV-1">
          <mxGeometry x="890" y="660" width="50" height="20" as="geometry" />
        </mxCell>
        <mxCell id="OIqggytlznoAPtVXcTWG-81" value="&lt;span style=&quot;font-size: 7px;&quot;&gt;no_telp&lt;/span&gt;" style="rounded=0;whiteSpace=wrap;html=1;" vertex="1" parent="WIyWlLk6GJQsqaUBKTNV-1">
          <mxGeometry x="890" y="560" width="50" height="20" as="geometry" />
        </mxCell>
      </root>
    </mxGraphModel>
  </diagram>
</mxfile>
